setup.py
simplefetion/__init__.py
simplefetion/simple_requests.py
simplefetion/simplefetion.py
simplefetion.egg-info/PKG-INFO
simplefetion.egg-info/SOURCES.txt
simplefetion.egg-info/dependency_links.txt
simplefetion.egg-info/not-zip-safe
simplefetion.egg-info/requires.txt
simplefetion.egg-info/top_level.txt