Metadata-Version: 1.1
Name: simplefetion
Version: 0.0.5
Summary: Simple Fetion: send message / group messages
Home-page: https://djangofetion.sinaapp.com/
Author: Cole Smith
Author-email: uniquecolesmith@gmail.com
License: UNKNOWN
Platform: UNKNOWN
Classifier: Development Status :: 5 - Production/Stable
Classifier: Intended Audience :: Developers
Classifier: Natural Language :: English
Classifier: License :: OSI Approved :: Apache Software License
Classifier: Programming Language :: Python
Classifier: Programming Language :: Python :: 2.6
Classifier: Programming Language :: Python :: 2.7
Classifier: Programming Language :: Python :: 3
Classifier: Programming Language :: Python :: 3.3
Classifier: Programming Language :: Python :: 3.4
